odoo/addons/mrp_production_auto_validate/README.rst
odoo/addons/mrp_production_auto_validate/__init__.py
odoo/addons/mrp_production_auto_validate/__manifest__.py
odoo/addons/mrp_production_auto_validate/i18n/es.po
odoo/addons/mrp_production_auto_validate/i18n/it.po
odoo/addons/mrp_production_auto_validate/i18n/mrp_production_auto_validate.pot
odoo/addons/mrp_production_auto_validate/models/__init__.py
odoo/addons/mrp_production_auto_validate/models/mrp_bom.py
odoo/addons/mrp_production_auto_validate/models/mrp_production.py
odoo/addons/mrp_production_auto_validate/models/stock_picking.py
odoo/addons/mrp_production_auto_validate/models/stock_rule.py
odoo/addons/mrp_production_auto_validate/readme/CONFIGURE.rst
odoo/addons/mrp_production_auto_validate/readme/CONTRIBUTORS.rst
odoo/addons/mrp_production_auto_validate/readme/DESCRIPTION.rst
odoo/addons/mrp_production_auto_validate/readme/ROADMAP.rst
odoo/addons/mrp_production_auto_validate/static/description/icon.png
odoo/addons/mrp_production_auto_validate/static/description/index.html
odoo/addons/mrp_production_auto_validate/tests/__init__.py
odoo/addons/mrp_production_auto_validate/tests/test_auto_validate.py
odoo/addons/mrp_production_auto_validate/views/mrp_bom.xml
odoo/addons/mrp_production_auto_validate/views/mrp_production.xml
odoo/addons/mrp_production_auto_validate/wizards/__init__.py
odoo/addons/mrp_production_auto_validate/wizards/mrp_production_backorder.py
odoo14_addon_mrp_production_auto_validate-14.0.1.0.1.dev12.dist-info/METADATA
odoo14_addon_mrp_production_auto_validate-14.0.1.0.1.dev12.dist-info/WHEEL
odoo14_addon_mrp_production_auto_validate-14.0.1.0.1.dev12.dist-info/top_level.txt
odoo14_addon_mrp_production_auto_validate-14.0.1.0.1.dev12.dist-info/RECORD
